odoo/addons/delivery_carrier_label_ups/README.rst
odoo/addons/delivery_carrier_label_ups/__init__.py
odoo/addons/delivery_carrier_label_ups/__manifest__.py
odoo/addons/delivery_carrier_label_ups/data/delivery_carrier.xml
odoo/addons/delivery_carrier_label_ups/data/delivery_carrier_template_option.xml
odoo/addons/delivery_carrier_label_ups/data/ir_config_parameter.xml
odoo/addons/delivery_carrier_label_ups/i18n/.empty
odoo/addons/delivery_carrier_label_ups/i18n/delivery_carrier_label_ups.pot
odoo/addons/delivery_carrier_label_ups/models/__init__.py
odoo/addons/delivery_carrier_label_ups/models/carrier_account.py
odoo/addons/delivery_carrier_label_ups/models/delivery_carrier.py
odoo/addons/delivery_carrier_label_ups/models/product_packaging.py
odoo/addons/delivery_carrier_label_ups/models/stock_picking.py
odoo/addons/delivery_carrier_label_ups/readme/CONFIGURE.rst
odoo/addons/delivery_carrier_label_ups/readme/CONTRIBUTORS.rst
odoo/addons/delivery_carrier_label_ups/readme/DESCRIPTION.rst
odoo/addons/delivery_carrier_label_ups/readme/ROADMAP.rst
odoo/addons/delivery_carrier_label_ups/readme/USAGE.rst
odoo/addons/delivery_carrier_label_ups/readme/newsfragments/.gitkeep
odoo/addons/delivery_carrier_label_ups/static/description/icon.png
odoo/addons/delivery_carrier_label_ups/static/description/index.html
odoo/addons/delivery_carrier_label_ups/tests/__init__.py
odoo/addons/delivery_carrier_label_ups/tests/test_delivery_carrier_label_ups.py
odoo/addons/delivery_carrier_label_ups/views/carrier_account.xml
odoo/addons/delivery_carrier_label_ups/views/product_packaging.xml
odoo12_addon_delivery_carrier_label_ups-12.0.1.2.1.dist-info/METADATA
odoo12_addon_delivery_carrier_label_ups-12.0.1.2.1.dist-info/WHEEL
odoo12_addon_delivery_carrier_label_ups-12.0.1.2.1.dist-info/top_level.txt
odoo12_addon_delivery_carrier_label_ups-12.0.1.2.1.dist-info/RECORD
